{"users":[{"date_birth":"1998-12-03","total_credits":"","average_mark":"","prev_diploma_number":"B20 №118855","prev_diploma_date":"2020-06-30","name_ukr":"Оксана","name_eng":"Oksana","diploma_theme_E":"Enhancing the Effectiveness of Dangerous Goods International Transportation","prev_navch_zakl":"Національний транспортний університет","date_diploma_receiving":"2022-01-31","course_works":[{"discipline_ukr":"Курсовий проект з дисципліни «Транспортно-експедиторська діяльність при виконанні міжнародних перевезень»","discipline_eng":"Course Project in Freight Forwarding Activities in International Transportation","national_grade":"Незараховано \/ Fail","credits":"5,0","ECTC":"F","mark":"0"},{"discipline_ukr":"Курсовий проект з дисципліни «Системний підхід до організації процесу доставки вантажів у міжнародному сполученні»","discipline_eng":"Course Project in System Approach to Freight Delivery in International Traffic","national_grade":"Відмінно \/Excellent","credits":"5,0","ECTC":"A","mark":"90"},{"discipline_ukr":"Курсова робота з дисципліни «Моделі та методи оптимізації перевезень у міжнародному сполученні»","discipline_eng":"Course Paper in Models and Optimization Methods for International Road Transportation","national_grade":"Відмінно \/Excellent","credits":"5,0","ECTC":"A","mark":"99"},{"discipline_ukr":"Курсова робота з дисципліни «Організація наукових досліджень у міжнародних перевезеннях»","discipline_eng":"Course Paper in Scientific Research in International Transportation","national_grade":"Відмінно \/Excellent","credits":"5,0","ECTC":"A","mark":"95"},{"discipline_ukr":"Розрахунково-графічна робота з дисципліни «Організація міжнародних перевезень спеціальних вантажів автомобільним транспортом»","discipline_eng":"Calculation and Graphic Work in International Road Transportation of Special Goods","national_grade":"Відмінно \/Excellent","credits":"4,0","ECTC":"A","mark":"90"},{"discipline_ukr":"Розрахунково-графічна робота з дисципліни «Стратегії управління транспортним підприємством»","discipline_eng":"Calculation and Graphic Work in Transport Enterprise Management Strategies","national_grade":"Відмінно \/Excellent","credits":"4,0","ECTC":"A","mark":"95"}],"middlename_ukr":"Сергіївна","diploma_theme":"Підвищення ефективності виконання перевезень небезпечних вантажів у міжнародному сполученні ","middlename_eng":"Serhiivna","diploma_type":"Диплом \/ Diploma","name_dok_osv":"Диплом бакалавра","average_grade":"","series_diploma":"М22","prev_navch_zakl_en":"National Transport University","average_ECTS":"","marks":[{"discipline_ukr":"Моделі та методи оптимізації перевезень у міжнародному сполученні","discipline_eng":"Models and Optimization Methods for International Road Transportation","national_grade":"Відмінно \/Excellent","credits":"5,0","ECTC":"A","mark":"99"},{"discipline_ukr":"Мультимодальні перевезення","discipline_eng":"Multimodal Transportation","national_grade":"Відмінно \/Excellent","credits":"4,0","ECTC":"A","mark":"96"},{"discipline_ukr":"Сучасні технології міжнародних перевезень","discipline_eng":"Modern International Transportation Technologies","national_grade":"Відмінно \/Excellent","credits":"4,0","ECTC":"A","mark":"90"},{"discipline_ukr":"Управління проектами соціальної та екологічної безпеки в транспортних системах","discipline_eng":"Management of Social and Environmental Safety Projects in Transport Systems","national_grade":"Незараховано \/ Fail","credits":"3,0","ECTC":"F","mark":"0"},{"discipline_ukr":"Інформаційно-комунікаційні технології на транспорті ","discipline_eng":"Information and Communication Technologies in Transport","national_grade":"Відмінно \/Excellent","credits":"3,0","ECTC":"A","mark":"90"},{"discipline_ukr":"Проблеми теорії та практики управління на транспорті","discipline_eng":"Problems of Theory and Practice of Transport Management","national_grade":"Відмінно \/Excellent","credits":"3,0","ECTC":"A","mark":"90"},{"discipline_ukr":"Транспортно-експедиторська діяльність при виконанні міжнародних перевезень","discipline_eng":"Freight Forwarding Activities in International Transportation","national_grade":"Незараховано \/ Fail","credits":"5,0","ECTC":"F","mark":"0"},{"discipline_ukr":"Системний підхід до організації процесу доставки вантажів у міжнародному сполученні","discipline_eng":"System Approach to Freight Delivery in International Traffic","national_grade":"Відмінно \/Excellent","credits":"5,0","ECTC":"A","mark":"90"},{"discipline_ukr":"Аутсорсинг транспортно-логістичних послуг","discipline_eng":"Outsourcing of Transport and Logistics Services","national_grade":"Відмінно \/Excellent","credits":"4,0","ECTC":"A","mark":"95"},{"discipline_ukr":"Організація міжнародних перевезень спеціальних вантажів автомобільним транспортом","discipline_eng":"International Road Transportation of Special Goods","national_grade":"Незараховано \/ Fail","credits":"4,0","ECTC":"F","mark":"0"},{"discipline_ukr":"Управління проектами в міжнародних перевезеннях","discipline_eng":"Project Management in International Transportation","national_grade":"Відмінно \/Excellent","credits":"4,0","ECTC":"A","mark":"90"},{"discipline_ukr":"Іноземна мова ділового спілкування","discipline_eng":"Business Foreign Language","national_grade":"Відмінно \/Excellent","credits":"4,0","ECTC":"A","mark":"90"},{"discipline_ukr":"Педагогіка та методика викладання у вищій школі","discipline_eng":"Pedagogy and Teaching Methods in High School","national_grade":"Відмінно \/Excellent","credits":"3,0","ECTC":"A","mark":"90"},{"discipline_ukr":"Стратегії управління транспортним підприємством","discipline_eng":"Transport Enterprise Management Strategies","national_grade":"Відмінно \/Excellent","credits":"4,0","ECTC":"A","mark":"95"},{"discipline_ukr":"Організація наукових досліджень у міжнародних перевезеннях","discipline_eng":"Scientific Research in International Transportation","national_grade":"Відмінно \/Excellent","credits":"5,0","ECTC":"A","mark":"93"}],"number_supplement_diploma":"9289103","number_diploma":"013046","surname_ukr":"Гаврилюк","practisies":[{"discipline_ukr":"Виробнича практика","discipline_eng":"Industrial Training (in Technology and Economics)","national_grade":"Відмінно \/Excellent","credits":"6,0","ECTC":"A","mark":"98"},{"discipline_ukr":"Науково-дослідницька практика","discipline_eng":"Research Practical Training","national_grade":"Відмінно \/Excellent","credits":"6,0","ECTC":"A","mark":"98"}],"date_receiving_supplement":"2022-01-31","surname_eng":"Havryliuk","atestation":{"discipline_ukr":"Виконання і захист кваліфікаційної роботи магістра","discipline_eng":null,"national_grade":"Відмінно \/Excellent","credits":"18,0","ECTC":"A","mark":"93"}},{"date_birth":"1998-11-23","total_credits":"","average_mark":"","prev_diploma_number":"B20 №118919","prev_diploma_date":"2020-06-30","name_ukr":"Анастасія","name_eng":"Anastasiia","diploma_theme_E":"Ways to Improve the Transport Process of Delivery of Goods in the Performance of International Transport","prev_navch_zakl":"Національний транспортний університет","date_diploma_receiving":"2022-01-31","course_works":[{"discipline_ukr":"Курсовий проект з дисципліни «Транспортно-експедиторська діяльність при виконанні міжнародних перевезень»","discipline_eng":"Course Project in Freight Forwarding Activities in International Transportation","national_grade":"Незараховано \/ Fail","credits":"5,0","ECTC":"F","mark":"0"},{"discipline_ukr":"Курсовий проект з дисципліни «Системний підхід до організації процесу доставки вантажів у міжнародному сполученні»","discipline_eng":"Course Project in System Approach to Freight Delivery in International Traffic","national_grade":"Добре \/ Good","credits":"5,0","ECTC":"C","mark":"78"},{"discipline_ukr":"Курсова робота з дисципліни «Моделі та методи оптимізації перевезень у міжнародному сполученні»","discipline_eng":"Course Paper in Models and Optimization Methods for International Road Transportation","national_grade":"Добре \/ Good","credits":"5,0","ECTC":"B","mark":"85"},{"discipline_ukr":"Курсова робота з дисципліни «Організація наукових досліджень у міжнародних перевезеннях»","discipline_eng":"Course Paper in Scientific Research in International Transportation","national_grade":"Відмінно \/Excellent","credits":"5,0","ECTC":"A","mark":"100"},{"discipline_ukr":"Розрахунково-графічна робота з дисципліни «Організація міжнародних перевезень спеціальних вантажів автомобільним транспортом»","discipline_eng":"Calculation and Graphic Work in International Road Transportation of Special Goods","national_grade":"Добре \/ Good","credits":"4,0","ECTC":"C","mark":"80"},{"discipline_ukr":"Розрахунково-графічна робота з дисципліни «Стратегії управління транспортним підприємством»","discipline_eng":"Calculation and Graphic Work in Transport Enterprise Management Strategies","national_grade":"Відмінно \/Excellent","credits":"4,0","ECTC":"A","mark":"95"}],"middlename_ukr":"Савеліївна","diploma_theme":"Шляхи удосконалення транспортного процесу доставки вантажів при виконанні міжнародних перевезень","middlename_eng":"Saveliivna","diploma_type":"Диплом \/ Diploma","name_dok_osv":"Диплом бакалавра","average_grade":"","series_diploma":"М22","prev_navch_zakl_en":"National Transport University","average_ECTS":"","marks":[{"discipline_ukr":"Моделі та методи оптимізації перевезень у міжнародному сполученні","discipline_eng":"Models and Optimization Methods for International Road Transportation","national_grade":"Добре \/ Good","credits":"5,0","ECTC":"B","mark":"85"},{"discipline_ukr":"Мультимодальні перевезення","discipline_eng":"Multimodal Transportation","national_grade":"Відмінно \/Excellent","credits":"4,0","ECTC":"A","mark":"95"},{"discipline_ukr":"Сучасні технології міжнародних перевезень","discipline_eng":"Modern International Transportation Technologies","national_grade":"Задовільно \/ Satisfactory","credits":"4,0","ECTC":"D","mark":"72"},{"discipline_ukr":"Управління проектами соціальної та екологічної безпеки в транспортних системах","discipline_eng":"Management of Social and Environmental Safety Projects in Transport Systems","national_grade":"Відмінно \/Excellent","credits":"3,0","ECTC":"A","mark":"90"},{"discipline_ukr":"Інформаційно-комунікаційні технології на транспорті ","discipline_eng":"Information and Communication Technologies in Transport","national_grade":"Відмінно \/Excellent","credits":"3,0","ECTC":"A","mark":"90"},{"discipline_ukr":"Проблеми теорії та практики управління на транспорті","discipline_eng":"Problems of Theory and Practice of Transport Management","national_grade":"Відмінно \/Excellent","credits":"3,0","ECTC":"A","mark":"92"},{"discipline_ukr":"Транспортно-експедиторська діяльність при виконанні міжнародних перевезень","discipline_eng":"Freight Forwarding Activities in International Transportation","national_grade":"Незараховано \/ Fail","credits":"5,0","ECTC":"F","mark":"0"},{"discipline_ukr":"Системний підхід до організації процесу доставки вантажів у міжнародному сполученні","discipline_eng":"System Approach to Freight Delivery in International Traffic","national_grade":"Відмінно \/Excellent","credits":"5,0","ECTC":"A","mark":"90"},{"discipline_ukr":"Аутсорсинг транспортно-логістичних послуг","discipline_eng":"Outsourcing of Transport and Logistics Services","national_grade":"Відмінно \/Excellent","credits":"4,0","ECTC":"A","mark":"92"},{"discipline_ukr":"Організація міжнародних перевезень спеціальних вантажів автомобільним транспортом","discipline_eng":"International Road Transportation of Special Goods","national_grade":"Добре \/ Good","credits":"4,0","ECTC":"C","mark":"80"},{"discipline_ukr":"Управління проектами в міжнародних перевезеннях","discipline_eng":"Project Management in International Transportation","national_grade":"Добре \/ Good","credits":"4,0","ECTC":"B","mark":"85"},{"discipline_ukr":"Іноземна мова ділового спілкування","discipline_eng":"Business Foreign Language","national_grade":"Добре \/ Good","credits":"4,0","ECTC":"C","mark":"77"},{"discipline_ukr":"Педагогіка та методика викладання у вищій школі","discipline_eng":"Pedagogy and Teaching Methods in High School","national_grade":"Добре \/ Good","credits":"3,0","ECTC":"C","mark":"74"},{"discipline_ukr":"Стратегії управління транспортним підприємством","discipline_eng":"Transport Enterprise Management Strategies","national_grade":"Відмінно \/Excellent","credits":"4,0","ECTC":"A","mark":"95"},{"discipline_ukr":"Організація наукових досліджень у міжнародних перевезеннях","discipline_eng":"Scientific Research in International Transportation","national_grade":"Відмінно \/Excellent","credits":"5,0","ECTC":"A","mark":"100"}],"number_supplement_diploma":"9288969","number_diploma":"013097","surname_ukr":"Дісяк","practisies":[{"discipline_ukr":"Виробнича практика","discipline_eng":"Industrial Training (in Technology and Economics)","national_grade":"Добре \/ Good","credits":"6,0","ECTC":"C","mark":"80"},{"discipline_ukr":"Науково-дослідницька практика","discipline_eng":"Research Practical Training","national_grade":"Добре \/ Good","credits":"6,0","ECTC":"C","mark":"80"}],"date_receiving_supplement":"2022-01-31","surname_eng":"Disiak","atestation":{"discipline_ukr":"Виконання і захист кваліфікаційної роботи магістра","discipline_eng":null,"national_grade":"Добре \/ Good","credits":"18,0","ECTC":"B","mark":"88"}},{"date_birth":"1998-12-27","total_credits":"","average_mark":"","prev_diploma_number":"B20 №118872","prev_diploma_date":"2020-06-30","name_ukr":"Денис","name_eng":"Denys","diploma_theme_E":"Increasing the Transport Process Efficiency Indicators of an International Automotive Goods Transportation","prev_navch_zakl":"Національний транспортний університет","date_diploma_receiving":"2022-01-31","course_works":[{"discipline_ukr":"Курсовий проект з дисципліни «Транспортно-експедиторська діяльність при виконанні міжнародних перевезень»","discipline_eng":"Course Project in Freight Forwarding Activities in International Transportation","national_grade":"Добре \/ Good","credits":"5,0","ECTC":"C","mark":"75"},{"discipline_ukr":"Курсовий проект з дисципліни «Системний підхід до організації процесу доставки вантажів у міжнародному сполученні»","discipline_eng":"Course Project in System Approach to Freight Delivery in International Traffic","national_grade":"Добре \/ Good","credits":"5,0","ECTC":"B","mark":"84"},{"discipline_ukr":"Курсова робота з дисципліни «Моделі та методи оптимізації перевезень у міжнародному сполученні»","discipline_eng":"Course Paper in Models and Optimization Methods for International Road Transportation","national_grade":"Відмінно \/Excellent","credits":"5,0","ECTC":"A","mark":"90"},{"discipline_ukr":"Курсова робота з дисципліни «Організація наукових досліджень у міжнародних перевезеннях»","discipline_eng":"Course Paper in Scientific Research in International Transportation","national_grade":"Відмінно \/Excellent","credits":"5,0","ECTC":"A","mark":"90"},{"discipline_ukr":"Розрахунково-графічна робота з дисципліни «Організація міжнародних перевезень спеціальних вантажів автомобільним транспортом»","discipline_eng":"Calculation and Graphic Work in International Road Transportation of Special Goods","national_grade":"Незараховано \/ Fail","credits":"4,0","ECTC":"F","mark":"0"},{"discipline_ukr":"Розрахунково-графічна робота з дисципліни «Стратегії управління транспортним підприємством»","discipline_eng":"Calculation and Graphic Work in Transport Enterprise Management Strategies","national_grade":"Відмінно \/Excellent","credits":"4,0","ECTC":"A","mark":"90"}],"middlename_ukr":"Олегович","diploma_theme":"Підвищення показників ефективності транспортного процесу міжнародних автомобільних перевезень вантажів","middlename_eng":"Olehovych","diploma_type":"Диплом \/ Diploma","name_dok_osv":"Диплом бакалавра","average_grade":"","series_diploma":"М22","prev_navch_zakl_en":"National Transport University","average_ECTS":"","marks":[{"discipline_ukr":"Моделі та методи оптимізації перевезень у міжнародному сполученні","discipline_eng":"Models and Optimization Methods for International Road Transportation","national_grade":"Відмінно \/Excellent","credits":"5,0","ECTC":"A","mark":"90"},{"discipline_ukr":"Мультимодальні перевезення","discipline_eng":"Multimodal Transportation","national_grade":"Відмінно \/Excellent","credits":"4,0","ECTC":"A","mark":"90"},{"discipline_ukr":"Сучасні технології міжнародних перевезень","discipline_eng":"Modern International Transportation Technologies","national_grade":"Відмінно \/Excellent","credits":"4,0","ECTC":"A","mark":"90"},{"discipline_ukr":"Управління проектами соціальної та екологічної безпеки в транспортних системах","discipline_eng":"Management of Social and Environmental Safety Projects in Transport Systems","national_grade":"Відмінно \/Excellent","credits":"3,0","ECTC":"A","mark":"90"},{"discipline_ukr":"Інформаційно-комунікаційні технології на транспорті ","discipline_eng":"Information and Communication Technologies in Transport","national_grade":"Добре \/ Good","credits":"3,0","ECTC":"B","mark":"82"},{"discipline_ukr":"Проблеми теорії та практики управління на транспорті","discipline_eng":"Problems of Theory and Practice of Transport Management","national_grade":"Відмінно \/Excellent","credits":"3,0","ECTC":"A","mark":"90"},{"discipline_ukr":"Транспортно-експедиторська діяльність при виконанні міжнародних перевезень","discipline_eng":"Freight Forwarding Activities in International Transportation","national_grade":"Добре \/ Good","credits":"5,0","ECTC":"C","mark":"75"},{"discipline_ukr":"Системний підхід до організації процесу доставки вантажів у міжнародному сполученні","discipline_eng":"System Approach to Freight Delivery in International Traffic","national_grade":"Добре \/ Good","credits":"5,0","ECTC":"B","mark":"82"},{"discipline_ukr":"Аутсорсинг транспортно-логістичних послуг","discipline_eng":"Outsourcing of Transport and Logistics Services","national_grade":"Добре \/ Good","credits":"4,0","ECTC":"B","mark":"86"},{"discipline_ukr":"Організація міжнародних перевезень спеціальних вантажів автомобільним транспортом","discipline_eng":"International Road Transportation of Special Goods","national_grade":"Незараховано \/ Fail","credits":"4,0","ECTC":"F","mark":"0"},{"discipline_ukr":"Управління проектами в міжнародних перевезеннях","discipline_eng":"Project Management in International Transportation","national_grade":"Добре \/ Good","credits":"4,0","ECTC":"B","mark":"84"},{"discipline_ukr":"Іноземна мова ділового спілкування","discipline_eng":"Business Foreign Language","national_grade":"Задовільно \/ Satisfactory","credits":"4,0","ECTC":"D","mark":"73"},{"discipline_ukr":"Педагогіка та методика викладання у вищій школі","discipline_eng":"Pedagogy and Teaching Methods in High School","national_grade":"Задовільно \/ Satisfactory","credits":"3,0","ECTC":"D","mark":"65"},{"discipline_ukr":"Стратегії управління транспортним підприємством","discipline_eng":"Transport Enterprise Management Strategies","national_grade":"Відмінно \/Excellent","credits":"4,0","ECTC":"A","mark":"90"},{"discipline_ukr":"Організація наукових досліджень у міжнародних перевезеннях","discipline_eng":"Scientific Research in International Transportation","national_grade":"Відмінно \/Excellent","credits":"5,0","ECTC":"A","mark":"93"}],"number_supplement_diploma":"9288970","number_diploma":"013098","surname_ukr":"Камінський","practisies":[{"discipline_ukr":"Виробнича практика","discipline_eng":"Industrial Training (in Technology and Economics)","national_grade":"Відмінно \/Excellent","credits":"6,0","ECTC":"A","mark":"90"},{"discipline_ukr":"Науково-дослідницька практика","discipline_eng":"Research Practical Training","national_grade":"Відмінно \/Excellent","credits":"6,0","ECTC":"A","mark":"90"}],"date_receiving_supplement":"2022-01-31","surname_eng":"Kaminskyi","atestation":{"discipline_ukr":"Виконання і захист кваліфікаційної роботи магістра","discipline_eng":null,"national_grade":"Добре \/ Good","credits":"18,0","ECTC":"B","mark":"82"}},{"date_birth":"1998-03-15","total_credits":"","average_mark":"","prev_diploma_number":"B20 №119062","prev_diploma_date":"2020-06-30","name_ukr":"Богдан","name_eng":"Bohdan","diploma_theme_E":"Improving the efficiency of foreign economic activity of the transport enterprise","prev_navch_zakl":"Національний транспортний університет","date_diploma_receiving":"2022-01-31","course_works":[{"discipline_ukr":"Курсовий проект з дисципліни «Транспортно-експедиторська діяльність при виконанні міжнародних перевезень»","discipline_eng":"Course Project in Freight Forwarding Activities in International Transportation","national_grade":"Задовільно \/ Satisfactory","credits":"5,0","ECTC":"E","mark":"60"},{"discipline_ukr":"Курсовий проект з дисципліни «Системний підхід до організації процесу доставки вантажів у міжнародному сполученні»","discipline_eng":"Course Project in System Approach to Freight Delivery in International Traffic","national_grade":"Задовільно \/ Satisfactory","credits":"5,0","ECTC":"D","mark":"70"},{"discipline_ukr":"Курсова робота з дисципліни «Моделі та методи оптимізації перевезень у міжнародному сполученні»","discipline_eng":"Course Paper in Models and Optimization Methods for International Road Transportation","national_grade":"Відмінно \/Excellent","credits":"5,0","ECTC":"A","mark":"90"},{"discipline_ukr":"Курсова робота з дисципліни «Організація наукових досліджень у міжнародних перевезеннях»","discipline_eng":"Course Paper in Scientific Research in International Transportation","national_grade":"Відмінно \/Excellent","credits":"5,0","ECTC":"A","mark":"100"},{"discipline_ukr":"Розрахунково-графічна робота з дисципліни «Організація міжнародних перевезень спеціальних вантажів автомобільним транспортом»","discipline_eng":"Calculation and Graphic Work in International Road Transportation of Special Goods","national_grade":"Задовільно \/ Satisfactory","credits":"4,0","ECTC":"D","mark":"70"},{"discipline_ukr":"Розрахунково-графічна робота з дисципліни «Стратегії управління транспортним підприємством»","discipline_eng":"Calculation and Graphic Work in Transport Enterprise Management Strategies","national_grade":"Добре \/ Good","credits":"4,0","ECTC":"C","mark":"75"}],"middlename_ukr":"Васильович","diploma_theme":"Підвищення ефективності зовнішньоекономічної діяльності транспортного підприємства ","middlename_eng":"Vasylovych","diploma_type":"Диплом \/ Diploma","name_dok_osv":"Диплом бакалавра","average_grade":"","series_diploma":"М22","prev_navch_zakl_en":"National Transport University","average_ECTS":"","marks":[{"discipline_ukr":"Моделі та методи оптимізації перевезень у міжнародному сполученні","discipline_eng":"Models and Optimization Methods for International Road Transportation","national_grade":"Відмінно \/Excellent","credits":"5,0","ECTC":"A","mark":"90"},{"discipline_ukr":"Мультимодальні перевезення","discipline_eng":"Multimodal Transportation","national_grade":"Відмінно \/Excellent","credits":"4,0","ECTC":"A","mark":"98"},{"discipline_ukr":"Сучасні технології міжнародних перевезень","discipline_eng":"Modern International Transportation Technologies","national_grade":"Задовільно \/ Satisfactory","credits":"4,0","ECTC":"D","mark":"72"},{"discipline_ukr":"Управління проектами соціальної та екологічної безпеки в транспортних системах","discipline_eng":"Management of Social and Environmental Safety Projects in Transport Systems","national_grade":"Добре \/ Good","credits":"3,0","ECTC":"B","mark":"85"},{"discipline_ukr":"Інформаційно-комунікаційні технології на транспорті ","discipline_eng":"Information and Communication Technologies in Transport","national_grade":"Добре \/ Good","credits":"3,0","ECTC":"B","mark":"82"},{"discipline_ukr":"Проблеми теорії та практики управління на транспорті","discipline_eng":"Problems of Theory and Practice of Transport Management","national_grade":"Добре \/ Good","credits":"3,0","ECTC":"C","mark":"75"},{"discipline_ukr":"Транспортно-експедиторська діяльність при виконанні міжнародних перевезень","discipline_eng":"Freight Forwarding Activities in International Transportation","national_grade":"Задовільно \/ Satisfactory","credits":"5,0","ECTC":"E","mark":"60"},{"discipline_ukr":"Системний підхід до організації процесу доставки вантажів у міжнародному сполученні","discipline_eng":"System Approach to Freight Delivery in International Traffic","national_grade":"Відмінно \/Excellent","credits":"5,0","ECTC":"A","mark":"90"},{"discipline_ukr":"Аутсорсинг транспортно-логістичних послуг","discipline_eng":"Outsourcing of Transport and Logistics Services","national_grade":"Добре \/ Good","credits":"4,0","ECTC":"B","mark":"88"},{"discipline_ukr":"Організація міжнародних перевезень спеціальних вантажів автомобільним транспортом","discipline_eng":"International Road Transportation of Special Goods","national_grade":"Задовільно \/ Satisfactory","credits":"4,0","ECTC":"D","mark":"70"},{"discipline_ukr":"Управління проектами в міжнародних перевезеннях","discipline_eng":"Project Management in International Transportation","national_grade":"Добре \/ Good","credits":"4,0","ECTC":"B","mark":"85"},{"discipline_ukr":"Іноземна мова ділового спілкування","discipline_eng":"Business Foreign Language","national_grade":"Задовільно \/ Satisfactory","credits":"4,0","ECTC":"D","mark":"67"},{"discipline_ukr":"Педагогіка та методика викладання у вищій школі","discipline_eng":"Pedagogy and Teaching Methods in High School","national_grade":"Задовільно \/ Satisfactory","credits":"3,0","ECTC":"D","mark":"70"},{"discipline_ukr":"Стратегії управління транспортним підприємством","discipline_eng":"Transport Enterprise Management Strategies","national_grade":"Добре \/ Good","credits":"4,0","ECTC":"C","mark":"75"},{"discipline_ukr":"Організація наукових досліджень у міжнародних перевезеннях","discipline_eng":"Scientific Research in International Transportation","national_grade":"Відмінно \/Excellent","credits":"5,0","ECTC":"A","mark":"100"}],"number_supplement_diploma":"9289105","number_diploma":"013114","surname_ukr":"Кущенко","practisies":[{"discipline_ukr":"Виробнича практика","discipline_eng":"Industrial Training (in Technology and Economics)","national_grade":"Відмінно \/Excellent","credits":"6,0","ECTC":"A","mark":"90"},{"discipline_ukr":"Науково-дослідницька практика","discipline_eng":"Research Practical Training","national_grade":"Відмінно \/Excellent","credits":"6,0","ECTC":"A","mark":"90"}],"date_receiving_supplement":"2022-01-31","surname_eng":"Kushchenko","atestation":{"discipline_ukr":"Виконання і захист кваліфікаційної роботи магістра","discipline_eng":null,"national_grade":"Добре \/ Good","credits":"18,0","ECTC":"C","mark":"78"}},{"date_birth":"1999-06-15","total_credits":"","average_mark":"","prev_diploma_number":"B20 №119014","prev_diploma_date":"2020-06-30","name_ukr":"Діана","name_eng":"Diana","diploma_theme_E":"Improving the efficiency of international freight","prev_navch_zakl":"Національний транспортний університет","date_diploma_receiving":"2022-01-31","course_works":[{"discipline_ukr":"Курсовий проект з дисципліни «Транспортно-експедиторська діяльність при виконанні міжнародних перевезень»","discipline_eng":"Course Project in Freight Forwarding Activities in International Transportation","national_grade":"Добре \/ Good","credits":"5,0","ECTC":"C","mark":"75"},{"discipline_ukr":"Курсовий проект з дисципліни «Системний підхід до організації процесу доставки вантажів у міжнародному сполученні»","discipline_eng":"Course Project in System Approach to Freight Delivery in International Traffic","national_grade":"Добре \/ Good","credits":"5,0","ECTC":"C","mark":"75"},{"discipline_ukr":"Курсова робота з дисципліни «Моделі та методи оптимізації перевезень у міжнародному сполученні»","discipline_eng":"Course Paper in Models and Optimization Methods for International Road Transportation","national_grade":"Відмінно \/Excellent","credits":"5,0","ECTC":"A","mark":"90"},{"discipline_ukr":"Курсова робота з дисципліни «Організація наукових досліджень у міжнародних перевезеннях»","discipline_eng":"Course Paper in Scientific Research in International Transportation","national_grade":"Відмінно \/Excellent","credits":"5,0","ECTC":"A","mark":"90"},{"discipline_ukr":"Розрахунково-графічна робота з дисципліни «Організація міжнародних перевезень спеціальних вантажів автомобільним транспортом»","discipline_eng":"Calculation and Graphic Work in International Road Transportation of Special Goods","national_grade":"Незараховано \/ Fail","credits":"4,0","ECTC":"F","mark":"0"},{"discipline_ukr":"Розрахунково-графічна робота з дисципліни «Стратегії управління транспортним підприємством»","discipline_eng":"Calculation and Graphic Work in Transport Enterprise Management Strategies","national_grade":"Відмінно \/Excellent","credits":"4,0","ECTC":"A","mark":"92"}],"middlename_ukr":"Русланівна","diploma_theme":"Підвищення ефективності міжнародних вантажних перевезень ","middlename_eng":"Ruslanivna","diploma_type":"Диплом \/ Diploma","name_dok_osv":"Диплом бакалавра","average_grade":"","series_diploma":"М22","prev_navch_zakl_en":"National Transport University","average_ECTS":"","marks":[{"discipline_ukr":"Моделі та методи оптимізації перевезень у міжнародному сполученні","discipline_eng":"Models and Optimization Methods for International Road Transportation","national_grade":"Відмінно \/Excellent","credits":"5,0","ECTC":"A","mark":"90"},{"discipline_ukr":"Мультимодальні перевезення","discipline_eng":"Multimodal Transportation","national_grade":"Відмінно \/Excellent","credits":"4,0","ECTC":"A","mark":"100"},{"discipline_ukr":"Сучасні технології міжнародних перевезень","discipline_eng":"Modern International Transportation Technologies","national_grade":"Відмінно \/Excellent","credits":"4,0","ECTC":"A","mark":"95"},{"discipline_ukr":"Управління проектами соціальної та екологічної безпеки в транспортних системах","discipline_eng":"Management of Social and Environmental Safety Projects in Transport Systems","national_grade":"Відмінно \/Excellent","credits":"3,0","ECTC":"A","mark":"90"},{"discipline_ukr":"Інформаційно-комунікаційні технології на транспорті ","discipline_eng":"Information and Communication Technologies in Transport","national_grade":"Відмінно \/Excellent","credits":"3,0","ECTC":"A","mark":"90"},{"discipline_ukr":"Проблеми теорії та практики управління на транспорті","discipline_eng":"Problems of Theory and Practice of Transport Management","national_grade":"Відмінно \/Excellent","credits":"3,0","ECTC":"A","mark":"92"},{"discipline_ukr":"Транспортно-експедиторська діяльність при виконанні міжнародних перевезень","discipline_eng":"Freight Forwarding Activities in International Transportation","national_grade":"Добре \/ Good","credits":"5,0","ECTC":"C","mark":"75"},{"discipline_ukr":"Системний підхід до організації процесу доставки вантажів у міжнародному сполученні","discipline_eng":"System Approach to Freight Delivery in International Traffic","national_grade":"Відмінно \/Excellent","credits":"5,0","ECTC":"A","mark":"92"},{"discipline_ukr":"Аутсорсинг транспортно-логістичних послуг","discipline_eng":"Outsourcing of Transport and Logistics Services","national_grade":"Відмінно \/Excellent","credits":"4,0","ECTC":"A","mark":"94"},{"discipline_ukr":"Організація міжнародних перевезень спеціальних вантажів автомобільним транспортом","discipline_eng":"International Road Transportation of Special Goods","national_grade":"Незараховано \/ Fail","credits":"4,0","ECTC":"F","mark":"0"},{"discipline_ukr":"Управління проектами в міжнародних перевезеннях","discipline_eng":"Project Management in International Transportation","national_grade":"Відмінно \/Excellent","credits":"4,0","ECTC":"A","mark":"92"},{"discipline_ukr":"Іноземна мова ділового спілкування","discipline_eng":"Business Foreign Language","national_grade":"Добре \/ Good","credits":"4,0","ECTC":"C","mark":"75"},{"discipline_ukr":"Педагогіка та методика викладання у вищій школі","discipline_eng":"Pedagogy and Teaching Methods in High School","national_grade":"Відмінно \/Excellent","credits":"3,0","ECTC":"A","mark":"90"},{"discipline_ukr":"Стратегії управління транспортним підприємством","discipline_eng":"Transport Enterprise Management Strategies","national_grade":"Відмінно \/Excellent","credits":"4,0","ECTC":"A","mark":"92"},{"discipline_ukr":"Організація наукових досліджень у міжнародних перевезеннях","discipline_eng":"Scientific Research in International Transportation","national_grade":"Відмінно \/Excellent","credits":"5,0","ECTC":"A","mark":"93"}],"number_supplement_diploma":"9288985","number_diploma":"013159","surname_ukr":"Солод","practisies":[{"discipline_ukr":"Виробнича практика","discipline_eng":"Industrial Training (in Technology and Economics)","national_grade":"Відмінно \/Excellent","credits":"6,0","ECTC":"A","mark":"90"},{"discipline_ukr":"Науково-дослідницька практика","discipline_eng":"Research Practical Training","national_grade":"Відмінно \/Excellent","credits":"6,0","ECTC":"A","mark":"90"}],"date_receiving_supplement":"2022-01-31","surname_eng":"Solod","atestation":{"discipline_ukr":"Виконання і захист кваліфікаційної роботи магістра","discipline_eng":null,"national_grade":"Добре \/ Good","credits":"18,0","ECTC":"C","mark":"80"}},{"date_birth":"1999-10-11","total_credits":"","average_mark":"","prev_diploma_number":"B20 №118937","prev_diploma_date":"2020-06-30","name_ukr":"Ольга","name_eng":"Olha","diploma_theme_E":"Efficiency Improvement of  Perishable Goods International Transportation ","prev_navch_zakl":"Національний транспортний університет","date_diploma_receiving":"2022-01-31","course_works":[{"discipline_ukr":"Курсовий проект з дисципліни «Транспортно-експедиторська діяльність при виконанні міжнародних перевезень»","discipline_eng":"Course Project in Freight Forwarding Activities in International Transportation","national_grade":"Добре \/ Good","credits":"5,0","ECTC":"C","mark":"80"},{"discipline_ukr":"Курсовий проект з дисципліни «Системний підхід до організації процесу доставки вантажів у міжнародному сполученні»","discipline_eng":"Course Project in System Approach to Freight Delivery in International Traffic","national_grade":"Відмінно \/Excellent","credits":"5,0","ECTC":"A","mark":"90"},{"discipline_ukr":"Курсова робота з дисципліни «Моделі та методи оптимізації перевезень у міжнародному сполученні»","discipline_eng":"Course Paper in Models and Optimization Methods for International Road Transportation","national_grade":"Відмінно \/Excellent","credits":"5,0","ECTC":"A","mark":"90"},{"discipline_ukr":"Курсова робота з дисципліни «Організація наукових досліджень у міжнародних перевезеннях»","discipline_eng":"Course Paper in Scientific Research in International Transportation","national_grade":"Відмінно \/Excellent","credits":"5,0","ECTC":"A","mark":"100"},{"discipline_ukr":"Розрахунково-графічна робота з дисципліни «Організація міжнародних перевезень спеціальних вантажів автомобільним транспортом»","discipline_eng":"Calculation and Graphic Work in International Road Transportation of Special Goods","national_grade":"Добре \/ Good","credits":"4,0","ECTC":"C","mark":"75"},{"discipline_ukr":"Розрахунково-графічна робота з дисципліни «Стратегії управління транспортним підприємством»","discipline_eng":"Calculation and Graphic Work in Transport Enterprise Management Strategies","national_grade":"Відмінно \/Excellent","credits":"4,0","ECTC":"A","mark":"90"}],"middlename_ukr":"Олександрівна","diploma_theme":"Підвищення ефективності виконання перевезень швидкопсувних вантажів у міжнародному сполученні ","middlename_eng":null,"diploma_type":"Диплом \/ Diploma","name_dok_osv":"Диплом бакалавра","average_grade":"","series_diploma":"М22","prev_navch_zakl_en":"National Transport University","average_ECTS":"","marks":[{"discipline_ukr":"Моделі та методи оптимізації перевезень у міжнародному сполученні","discipline_eng":"Models and Optimization Methods for International Road Transportation","national_grade":"Відмінно \/Excellent","credits":"5,0","ECTC":"A","mark":"90"},{"discipline_ukr":"Мультимодальні перевезення","discipline_eng":"Multimodal Transportation","national_grade":"Відмінно \/Excellent","credits":"4,0","ECTC":"A","mark":"100"},{"discipline_ukr":"Сучасні технології міжнародних перевезень","discipline_eng":"Modern International Transportation Technologies","national_grade":"Відмінно \/Excellent","credits":"4,0","ECTC":"A","mark":"90"},{"discipline_ukr":"Управління проектами соціальної та екологічної безпеки в транспортних системах","discipline_eng":"Management of Social and Environmental Safety Projects in Transport Systems","national_grade":"Відмінно \/Excellent","credits":"3,0","ECTC":"A","mark":"95"},{"discipline_ukr":"Інформаційно-комунікаційні технології на транспорті ","discipline_eng":"Information and Communication Technologies in Transport","national_grade":"Відмінно \/Excellent","credits":"3,0","ECTC":"A","mark":"90"},{"discipline_ukr":"Проблеми теорії та практики управління на транспорті","discipline_eng":"Problems of Theory and Practice of Transport Management","national_grade":"Добре \/ Good","credits":"3,0","ECTC":"B","mark":"85"},{"discipline_ukr":"Транспортно-експедиторська діяльність при виконанні міжнародних перевезень","discipline_eng":"Freight Forwarding Activities in International Transportation","national_grade":"Добре \/ Good","credits":"5,0","ECTC":"C","mark":"80"},{"discipline_ukr":"Системний підхід до організації процесу доставки вантажів у міжнародному сполученні","discipline_eng":"System Approach to Freight Delivery in International Traffic","national_grade":"Відмінно \/Excellent","credits":"5,0","ECTC":"A","mark":"95"},{"discipline_ukr":"Аутсорсинг транспортно-логістичних послуг","discipline_eng":"Outsourcing of Transport and Logistics Services","national_grade":"Відмінно \/Excellent","credits":"4,0","ECTC":"A","mark":"90"},{"discipline_ukr":"Організація міжнародних перевезень спеціальних вантажів автомобільним транспортом","discipline_eng":"International Road Transportation of Special Goods","national_grade":"Незараховано \/ Fail","credits":"4,0","ECTC":"F","mark":"0"},{"discipline_ukr":"Управління проектами в міжнародних перевезеннях","discipline_eng":"Project Management in International Transportation","national_grade":"Відмінно \/Excellent","credits":"4,0","ECTC":"A","mark":"92"},{"discipline_ukr":"Іноземна мова ділового спілкування","discipline_eng":"Business Foreign Language","national_grade":"Добре \/ Good","credits":"4,0","ECTC":"C","mark":"80"},{"discipline_ukr":"Педагогіка та методика викладання у вищій школі","discipline_eng":"Pedagogy and Teaching Methods in High School","national_grade":"Добре \/ Good","credits":"3,0","ECTC":"C","mark":"75"},{"discipline_ukr":"Стратегії управління транспортним підприємством","discipline_eng":"Transport Enterprise Management Strategies","national_grade":"Відмінно \/Excellent","credits":"4,0","ECTC":"A","mark":"90"},{"discipline_ukr":"Організація наукових досліджень у міжнародних перевезеннях","discipline_eng":"Scientific Research in International Transportation","national_grade":"Відмінно \/Excellent","credits":"5,0","ECTC":"A","mark":"100"}],"number_supplement_diploma":"9327465","number_diploma":"013121","surname_ukr":"Камінська","practisies":[{"discipline_ukr":"Виробнича практика","discipline_eng":"Industrial Training (in Technology and Economics)","national_grade":"Відмінно \/Excellent","credits":"6,0","ECTC":"A","mark":"90"},{"discipline_ukr":"Науково-дослідницька практика","discipline_eng":"Research Practical Training","national_grade":"Відмінно \/Excellent","credits":"6,0","ECTC":"A","mark":"90"}],"date_receiving_supplement":"2022-01-31","surname_eng":"Kaminska ","atestation":{"discipline_ukr":"Виконання і захист кваліфікаційної роботи магістра","discipline_eng":null,"national_grade":"Добре \/ Good","credits":"18,0","ECTC":"B","mark":"85"}},{"date_birth":"1997-04-10","total_credits":"","average_mark":"","prev_diploma_number":"B20 №119100","prev_diploma_date":"2020-06-30","name_ukr":"Дар`я","name_eng":"Daria","diploma_theme_E":"Improving the Efficiency of International Road Transport of Goods","prev_navch_zakl":"Національний транспортний університет","date_diploma_receiving":"2022-01-31","course_works":[{"discipline_ukr":"Курсовий проект з дисципліни «Транспортно-експедиторська діяльність при виконанні міжнародних перевезень»","discipline_eng":"Course Project in Freight Forwarding Activities in International Transportation","national_grade":"Задовільно \/ Satisfactory","credits":"5,0","ECTC":"D","mark":"70"},{"discipline_ukr":"Курсовий проект з дисципліни «Системний підхід до організації процесу доставки вантажів у міжнародному сполученні»","discipline_eng":"Course Project in System Approach to Freight Delivery in International Traffic","national_grade":"Відмінно \/Excellent","credits":"5,0","ECTC":"A","mark":"90"},{"discipline_ukr":"Курсова робота з дисципліни «Моделі та методи оптимізації перевезень у міжнародному сполученні»","discipline_eng":"Course Paper in Models and Optimization Methods for International Road Transportation","national_grade":"Відмінно \/Excellent","credits":"5,0","ECTC":"A","mark":"90"},{"discipline_ukr":"Курсова робота з дисципліни «Організація наукових досліджень у міжнародних перевезеннях»","discipline_eng":"Course Paper in Scientific Research in International Transportation","national_grade":"Добре \/ Good","credits":"5,0","ECTC":"C","mark":"80"},{"discipline_ukr":"Розрахунково-графічна робота з дисципліни «Організація міжнародних перевезень спеціальних вантажів автомобільним транспортом»","discipline_eng":"Calculation and Graphic Work in International Road Transportation of Special Goods","national_grade":"Незараховано \/ Fail","credits":"4,0","ECTC":"F","mark":"0"},{"discipline_ukr":"Розрахунково-графічна робота з дисципліни «Стратегії управління транспортним підприємством»","discipline_eng":"Calculation and Graphic Work in Transport Enterprise Management Strategies","national_grade":"Добре \/ Good","credits":"4,0","ECTC":"B","mark":"82"}],"middlename_ukr":"Ігорівна","diploma_theme":"Підвищення ефективності міжнародних перевезень вантажів автомобільним транспортом","middlename_eng":null,"diploma_type":"Диплом \/ Diploma","name_dok_osv":"Диплом бакалавра","average_grade":"","series_diploma":"М22","prev_navch_zakl_en":"National Transport University","average_ECTS":"","marks":[{"discipline_ukr":"Моделі та методи оптимізації перевезень у міжнародному сполученні","discipline_eng":"Models and Optimization Methods for International Road Transportation","national_grade":"Відмінно \/Excellent","credits":"5,0","ECTC":"A","mark":"90"},{"discipline_ukr":"Мультимодальні перевезення","discipline_eng":"Multimodal Transportation","national_grade":"Добре \/ Good","credits":"4,0","ECTC":"B","mark":"85"},{"discipline_ukr":"Сучасні технології міжнародних перевезень","discipline_eng":"Modern International Transportation Technologies","national_grade":"Добре \/ Good","credits":"4,0","ECTC":"B","mark":"82"},{"discipline_ukr":"Управління проектами соціальної та екологічної безпеки в транспортних системах","discipline_eng":"Management of Social and Environmental Safety Projects in Transport Systems","national_grade":"Відмінно \/Excellent","credits":"3,0","ECTC":"A","mark":"95"},{"discipline_ukr":"Інформаційно-комунікаційні технології на транспорті ","discipline_eng":"Information and Communication Technologies in Transport","national_grade":"Добре \/ Good","credits":"3,0","ECTC":"B","mark":"82"},{"discipline_ukr":"Проблеми теорії та практики управління на транспорті","discipline_eng":"Problems of Theory and Practice of Transport Management","national_grade":"Відмінно \/Excellent","credits":"3,0","ECTC":"A","mark":"90"},{"discipline_ukr":"Транспортно-експедиторська діяльність при виконанні міжнародних перевезень","discipline_eng":"Freight Forwarding Activities in International Transportation","national_grade":"Задовільно \/ Satisfactory","credits":"5,0","ECTC":"D","mark":"70"},{"discipline_ukr":"Системний підхід до організації процесу доставки вантажів у міжнародному сполученні","discipline_eng":"System Approach to Freight Delivery in International Traffic","national_grade":"Відмінно \/Excellent","credits":"5,0","ECTC":"A","mark":"90"},{"discipline_ukr":"Аутсорсинг транспортно-логістичних послуг","discipline_eng":"Outsourcing of Transport and Logistics Services","national_grade":"Відмінно \/Excellent","credits":"4,0","ECTC":"A","mark":"90"},{"discipline_ukr":"Організація міжнародних перевезень спеціальних вантажів автомобільним транспортом","discipline_eng":"International Road Transportation of Special Goods","national_grade":"Незараховано \/ Fail","credits":"4,0","ECTC":"F","mark":"0"},{"discipline_ukr":"Управління проектами в міжнародних перевезеннях","discipline_eng":"Project Management in International Transportation","national_grade":"Добре \/ Good","credits":"4,0","ECTC":"B","mark":"85"},{"discipline_ukr":"Іноземна мова ділового спілкування","discipline_eng":"Business Foreign Language","national_grade":"Добре \/ Good","credits":"4,0","ECTC":"C","mark":"75"},{"discipline_ukr":"Педагогіка та методика викладання у вищій школі","discipline_eng":"Pedagogy and Teaching Methods in High School","national_grade":"Добре \/ Good","credits":"3,0","ECTC":"C","mark":"75"},{"discipline_ukr":"Стратегії управління транспортним підприємством","discipline_eng":"Transport Enterprise Management Strategies","national_grade":"Добре \/ Good","credits":"4,0","ECTC":"B","mark":"82"},{"discipline_ukr":"Організація наукових досліджень у міжнародних перевезеннях","discipline_eng":"Scientific Research in International Transportation","national_grade":"Добре \/ Good","credits":"5,0","ECTC":"B","mark":"83"}],"number_supplement_diploma":"9327466","number_diploma":"013122","surname_ukr":"Пугач","practisies":[{"discipline_ukr":"Виробнича практика","discipline_eng":"Industrial Training (in Technology and Economics)","national_grade":"Відмінно \/Excellent","credits":"6,0","ECTC":"A","mark":"90"},{"discipline_ukr":"Науково-дослідницька практика","discipline_eng":"Research Practical Training","national_grade":"Відмінно \/Excellent","credits":"6,0","ECTC":"A","mark":"90"}],"date_receiving_supplement":"2022-01-31","surname_eng":"Puhach ","atestation":{"discipline_ukr":"Виконання і захист кваліфікаційної роботи магістра","discipline_eng":null,"national_grade":"Добре \/ Good","credits":"18,0","ECTC":"B","mark":"86"}},{"date_birth":"1999-08-06","total_credits":"","average_mark":"","prev_diploma_number":" B21 162167","prev_diploma_date":"2021-06-30","name_ukr":"Микола","name_eng":"Mykola","diploma_theme_E":"","prev_navch_zakl":"Національний транспортний університет","date_diploma_receiving":"","course_works":[{"discipline_ukr":"Курсовий проект з дисципліни «Системний підхід до організації процесу доставки вантажів у міжнародному сполученні»","discipline_eng":"Course Project in System Approach to Freight Delivery in International Traffic","national_grade":"Добре \/ Good","credits":"5,0","ECTC":"C","mark":"78"}],"middlename_ukr":"Олександрович","diploma_theme":"","middlename_eng":null,"diploma_type":"Диплом \/ Diploma","name_dok_osv":"Диплом бакалавра ","average_grade":"","series_diploma":"","prev_navch_zakl_en":null,"average_ECTS":"","marks":[{"discipline_ukr":"Управління проектами соціальної та екологічної безпеки в транспортних системах","discipline_eng":"Management of Social and Environmental Safety Projects in Transport Systems","national_grade":"Незараховано \/ Fail","credits":"3,0","ECTC":"F","mark":"0"},{"discipline_ukr":"Системний підхід до організації процесу доставки вантажів у міжнародному сполученні","discipline_eng":"System Approach to Freight Delivery in International Traffic","national_grade":"Добре \/ Good","credits":"5,0","ECTC":"C","mark":"80"},{"discipline_ukr":"Аутсорсинг транспортно-логістичних послуг","discipline_eng":"Outsourcing of Transport and Logistics Services","national_grade":"Задовільно \/ Satisfactory","credits":"4,0","ECTC":"E","mark":"60"}],"number_supplement_diploma":"","number_diploma":"","surname_ukr":"Бузина","practisies":[],"date_receiving_supplement":"","surname_eng":"Buzyna","atestation":{"discipline_ukr":"1","discipline_eng":"1","national_grade":"Задовільно \/ Satisfactory","credits":"2,0","ECTC":"D","mark":"70"}},{"date_birth":"1999-03-12","total_credits":"","average_mark":"","prev_diploma_number":" B21 182449","prev_diploma_date":"2021-06-30","name_ukr":"Олексій","name_eng":"Oleksii","diploma_theme_E":"","prev_navch_zakl":"Національний транспортний університет","date_diploma_receiving":"","course_works":[{"discipline_ukr":"Курсовий проект з дисципліни «Системний підхід до організації процесу доставки вантажів у міжнародному сполученні»","discipline_eng":"Course Project in System Approach to Freight Delivery in International Traffic","national_grade":"Добре \/ Good","credits":"5,0","ECTC":"C","mark":"75"}],"middlename_ukr":"Андрійович","diploma_theme":"","middlename_eng":"Andriiovych","diploma_type":"Диплом \/ Diploma","name_dok_osv":"Диплом бакалавра ","average_grade":"","series_diploma":"","prev_navch_zakl_en":null,"average_ECTS":"","marks":[{"discipline_ukr":"Управління проектами соціальної та екологічної безпеки в транспортних системах","discipline_eng":"Management of Social and Environmental Safety Projects in Transport Systems","national_grade":"Добре \/ Good","credits":"3,0","ECTC":"B","mark":"82"},{"discipline_ukr":"Системний підхід до організації процесу доставки вантажів у міжнародному сполученні","discipline_eng":"System Approach to Freight Delivery in International Traffic","national_grade":"Добре \/ Good","credits":"5,0","ECTC":"B","mark":"82"},{"discipline_ukr":"Аутсорсинг транспортно-логістичних послуг","discipline_eng":"Outsourcing of Transport and Logistics Services","national_grade":"Добре \/ Good","credits":"4,0","ECTC":"C","mark":"81"}],"number_supplement_diploma":"","number_diploma":"","surname_ukr":"Євсеєв","practisies":[],"date_receiving_supplement":"","surname_eng":"Yevseiev","atestation":{"discipline_ukr":"1","discipline_eng":"1","national_grade":"Задовільно \/ Satisfactory","credits":"2,0","ECTC":"D","mark":"70"}},{"date_birth":"1999-04-08","total_credits":"","average_mark":"","prev_diploma_number":" B21 162385","prev_diploma_date":"2021-06-30","name_ukr":"Артем","name_eng":"Artem","diploma_theme_E":null,"prev_navch_zakl":"Національний транспортний університет","date_diploma_receiving":null,"course_works":[{"discipline_ukr":"Курсовий проект з дисципліни «Системний підхід до організації процесу доставки вантажів у міжнародному сполученні»","discipline_eng":"Course Project in System Approach to Freight Delivery in International Traffic","national_grade":"Незараховано \/ Fail","credits":"5,0","ECTC":"F","mark":"0"}],"middlename_ukr":"Сергійович","diploma_theme":null,"middlename_eng":null,"diploma_type":"Диплом \/ Diploma","name_dok_osv":"Диплом бакалавра ","average_grade":"","series_diploma":null,"prev_navch_zakl_en":null,"average_ECTS":"","marks":[{"discipline_ukr":"Управління проектами соціальної та екологічної безпеки в транспортних системах","discipline_eng":"Management of Social and Environmental Safety Projects in Transport Systems","national_grade":"Незараховано \/ Fail","credits":"3,0","ECTC":"F","mark":"0"},{"discipline_ukr":"Системний підхід до організації процесу доставки вантажів у міжнародному сполученні","discipline_eng":"System Approach to Freight Delivery in International Traffic","national_grade":"Незараховано \/ Fail","credits":"5,0","ECTC":"F","mark":"0"},{"discipline_ukr":"Аутсорсинг транспортно-логістичних послуг","discipline_eng":"Outsourcing of Transport and Logistics Services","national_grade":"Незараховано \/ Fail","credits":"4,0","ECTC":"F","mark":"0"}],"number_supplement_diploma":null,"number_diploma":null,"surname_ukr":"Кравчук","practisies":[],"date_receiving_supplement":null,"surname_eng":"Kravchuk","atestation":{"discipline_ukr":"1","discipline_eng":"1","national_grade":"Задовільно \/ Satisfactory","credits":"2,0","ECTC":"D","mark":"70"}},{"date_birth":"1999-10-08","total_credits":"","average_mark":"","prev_diploma_number":" B21 162337","prev_diploma_date":"2021-06-30","name_ukr":"Денис","name_eng":"Denys","diploma_theme_E":"","prev_navch_zakl":"Національний транспортний університет","date_diploma_receiving":"","course_works":[{"discipline_ukr":"Курсовий проект з дисципліни «Системний підхід до організації процесу доставки вантажів у міжнародному сполученні»","discipline_eng":"Course Project in System Approach to Freight Delivery in International Traffic","national_grade":"Незараховано \/ Fail","credits":"5,0","ECTC":"F","mark":"0"}],"middlename_ukr":"Олегович","diploma_theme":"","middlename_eng":null,"diploma_type":"Диплом \/ Diploma","name_dok_osv":"Диплом бакалавра ","average_grade":"","series_diploma":"","prev_navch_zakl_en":null,"average_ECTS":"","marks":[{"discipline_ukr":"Управління проектами соціальної та екологічної безпеки в транспортних системах","discipline_eng":"Management of Social and Environmental Safety Projects in Transport Systems","national_grade":"Відмінно \/Excellent","credits":"3,0","ECTC":"A","mark":"90"},{"discipline_ukr":"Системний підхід до організації процесу доставки вантажів у міжнародному сполученні","discipline_eng":"System Approach to Freight Delivery in International Traffic","national_grade":"Незараховано \/ Fail","credits":"5,0","ECTC":"F","mark":"0"},{"discipline_ukr":"Аутсорсинг транспортно-логістичних послуг","discipline_eng":"Outsourcing of Transport and Logistics Services","national_grade":"Добре \/ Good","credits":"4,0","ECTC":"B","mark":"85"}],"number_supplement_diploma":"","number_diploma":"","surname_ukr":"Лисенко","practisies":[],"date_receiving_supplement":"","surname_eng":"Lysenko","atestation":{"discipline_ukr":"1","discipline_eng":"1","national_grade":"Задовільно \/ Satisfactory","credits":"2,0","ECTC":"D","mark":"70"}},{"date_birth":"2000-05-03","total_credits":"","average_mark":"","prev_diploma_number":" B21 162313","prev_diploma_date":"2021-06-30","name_ukr":"Микита","name_eng":"Mykyta","diploma_theme_E":"","prev_navch_zakl":"Національний транспортний університет","date_diploma_receiving":"","course_works":[{"discipline_ukr":"Курсовий проект з дисципліни «Системний підхід до організації процесу доставки вантажів у міжнародному сполученні»","discipline_eng":"Course Project in System Approach to Freight Delivery in International Traffic","national_grade":"Добре \/ Good","credits":"5,0","ECTC":"C","mark":"75"}],"middlename_ukr":"Сергійович","diploma_theme":"","middlename_eng":null,"diploma_type":"Диплом \/ Diploma","name_dok_osv":"Диплом бакалавра ","average_grade":"","series_diploma":"","prev_navch_zakl_en":null,"average_ECTS":"","marks":[{"discipline_ukr":"Управління проектами соціальної та екологічної безпеки в транспортних системах","discipline_eng":"Management of Social and Environmental Safety Projects in Transport Systems","national_grade":"Добре \/ Good","credits":"3,0","ECTC":"C","mark":"75"},{"discipline_ukr":"Системний підхід до організації процесу доставки вантажів у міжнародному сполученні","discipline_eng":"System Approach to Freight Delivery in International Traffic","national_grade":"Добре \/ Good","credits":"5,0","ECTC":"B","mark":"82"},{"discipline_ukr":"Аутсорсинг транспортно-логістичних послуг","discipline_eng":"Outsourcing of Transport and Logistics Services","national_grade":"Добре \/ Good","credits":"4,0","ECTC":"B","mark":"85"}],"number_supplement_diploma":"","number_diploma":"","surname_ukr":"Мельников","practisies":[],"date_receiving_supplement":"","surname_eng":"Melnykov","atestation":{"discipline_ukr":"1","discipline_eng":"1","national_grade":"Задовільно \/ Satisfactory","credits":"2,0","ECTC":"D","mark":"70"}},{"date_birth":"2000-01-04","total_credits":"","average_mark":"","prev_diploma_number":" B21 162322","prev_diploma_date":"2021-06-30","name_ukr":"Богдан","name_eng":"Bohdan","diploma_theme_E":null,"prev_navch_zakl":"Національний транспортний університет","date_diploma_receiving":null,"course_works":[{"discipline_ukr":"Курсовий проект з дисципліни «Системний підхід до організації процесу доставки вантажів у міжнародному сполученні»","discipline_eng":"Course Project in System Approach to Freight Delivery in International Traffic","national_grade":"Незараховано \/ Fail","credits":"5,0","ECTC":"F","mark":"0"}],"middlename_ukr":"Юрійович","diploma_theme":null,"middlename_eng":null,"diploma_type":"Диплом \/ Diploma","name_dok_osv":"Диплом бакалавра ","average_grade":"","series_diploma":null,"prev_navch_zakl_en":null,"average_ECTS":"","marks":[{"discipline_ukr":"Управління проектами соціальної та екологічної безпеки в транспортних системах","discipline_eng":"Management of Social and Environmental Safety Projects in Transport Systems","national_grade":"Незараховано \/ Fail","credits":"3,0","ECTC":"F","mark":"0"},{"discipline_ukr":"Системний підхід до організації процесу доставки вантажів у міжнародному сполученні","discipline_eng":"System Approach to Freight Delivery in International Traffic","national_grade":"Незараховано \/ Fail","credits":"5,0","ECTC":"F","mark":"0"},{"discipline_ukr":"Аутсорсинг транспортно-логістичних послуг","discipline_eng":"Outsourcing of Transport and Logistics Services","national_grade":"Незараховано \/ Fail","credits":"4,0","ECTC":"F","mark":"0"}],"number_supplement_diploma":null,"number_diploma":null,"surname_ukr":"Петренко","practisies":[],"date_receiving_supplement":null,"surname_eng":"Petrenko","atestation":{"discipline_ukr":"1","discipline_eng":"1","national_grade":"Задовільно \/ Satisfactory","credits":"2,0","ECTC":"D","mark":"70"}},{"date_birth":"1999-12-19","total_credits":"","average_mark":"","prev_diploma_number":" B21 162435","prev_diploma_date":"2021-06-30","name_ukr":"Микола","name_eng":"Mykola","diploma_theme_E":"","prev_navch_zakl":"Національний транспортний університет","date_diploma_receiving":"","course_works":[{"discipline_ukr":"Курсовий проект з дисципліни «Системний підхід до організації процесу доставки вантажів у міжнародному сполученні»","discipline_eng":"Course Project in System Approach to Freight Delivery in International Traffic","national_grade":"Незараховано \/ Fail","credits":"5,0","ECTC":"F","mark":"0"}],"middlename_ukr":"Володимирович","diploma_theme":"","middlename_eng":null,"diploma_type":"Диплом \/ Diploma","name_dok_osv":"Диплом бакалавра ","average_grade":"","series_diploma":"","prev_navch_zakl_en":null,"average_ECTS":"","marks":[{"discipline_ukr":"Управління проектами соціальної та екологічної безпеки в транспортних системах","discipline_eng":"Management of Social and Environmental Safety Projects in Transport Systems","national_grade":"Незараховано \/ Fail","credits":"3,0","ECTC":"F","mark":"0"},{"discipline_ukr":"Системний підхід до організації процесу доставки вантажів у міжнародному сполученні","discipline_eng":"System Approach to Freight Delivery in International Traffic","national_grade":"Незараховано \/ Fail","credits":"5,0","ECTC":"F","mark":"0"},{"discipline_ukr":"Аутсорсинг транспортно-логістичних послуг","discipline_eng":"Outsourcing of Transport and Logistics Services","national_grade":"Незараховано \/ Fail","credits":"4,0","ECTC":"F","mark":"0"}],"number_supplement_diploma":"","number_diploma":"","surname_ukr":"Смусь","practisies":[],"date_receiving_supplement":"","surname_eng":"Smus","atestation":{"discipline_ukr":"1","discipline_eng":"1","national_grade":"Задовільно \/ Satisfactory","credits":"2,0","ECTC":"D","mark":"70"}},{"date_birth":"2000-08-14","total_credits":"","average_mark":"","prev_diploma_number":" B21 162155","prev_diploma_date":"2021-06-30","name_ukr":"Ірина","name_eng":"Iryna","diploma_theme_E":"","prev_navch_zakl":"Національний транспортний університет","date_diploma_receiving":"","course_works":[{"discipline_ukr":"Курсовий проект з дисципліни «Системний підхід до організації процесу доставки вантажів у міжнародному сполученні»","discipline_eng":"Course Project in System Approach to Freight Delivery in International Traffic","national_grade":"Відмінно \/Excellent","credits":"5,0","ECTC":"A","mark":"90"}],"middlename_ukr":"Володимирівна","diploma_theme":"","middlename_eng":null,"diploma_type":"Диплом \/ Diploma","name_dok_osv":"Диплом бакалавра ","average_grade":"","series_diploma":"","prev_navch_zakl_en":null,"average_ECTS":"","marks":[{"discipline_ukr":"Управління проектами соціальної та екологічної безпеки в транспортних системах","discipline_eng":"Management of Social and Environmental Safety Projects in Transport Systems","national_grade":"Відмінно \/Excellent","credits":"3,0","ECTC":"A","mark":"90"},{"discipline_ukr":"Системний підхід до організації процесу доставки вантажів у міжнародному сполученні","discipline_eng":"System Approach to Freight Delivery in International Traffic","national_grade":"Відмінно \/Excellent","credits":"5,0","ECTC":"A","mark":"92"},{"discipline_ukr":"Аутсорсинг транспортно-логістичних послуг","discipline_eng":"Outsourcing of Transport and Logistics Services","national_grade":"Відмінно \/Excellent","credits":"4,0","ECTC":"A","mark":"93"}],"number_supplement_diploma":"","number_diploma":"","surname_ukr":"Грановська","practisies":[],"date_receiving_supplement":"","surname_eng":"Hranovska","atestation":{"discipline_ukr":"1","discipline_eng":"1","national_grade":"Задовільно \/ Satisfactory","credits":"2,0","ECTC":"D","mark":"70"}},{"date_birth":"1998-01-02","total_credits":"","average_mark":"","prev_diploma_number":null,"prev_diploma_date":null,"name_ukr":"Семен","name_eng":null,"diploma_theme_E":null,"prev_navch_zakl":null,"date_diploma_receiving":null,"course_works":[{"discipline_ukr":"Курсовий проект з дисципліни «Системний підхід до організації процесу доставки вантажів у міжнародному сполученні»","discipline_eng":"Course Project in System Approach to Freight Delivery in International Traffic","national_grade":"Відмінно \/Excellent","credits":"5,0","ECTC":"A","mark":"90"}],"middlename_ukr":"Тарасович","diploma_theme":null,"middlename_eng":null,"diploma_type":"Диплом \/ Diploma","name_dok_osv":null,"average_grade":"","series_diploma":null,"prev_navch_zakl_en":null,"average_ECTS":"","marks":[{"discipline_ukr":"Управління проектами соціальної та екологічної безпеки в транспортних системах","discipline_eng":"Management of Social and Environmental Safety Projects in Transport Systems","national_grade":"Відмінно \/Excellent","credits":"3,0","ECTC":"A","mark":"90"},{"discipline_ukr":"Системний підхід до організації процесу доставки вантажів у міжнародному сполученні","discipline_eng":"System Approach to Freight Delivery in International Traffic","national_grade":"Відмінно \/Excellent","credits":"5,0","ECTC":"A","mark":"92"},{"discipline_ukr":"Аутсорсинг транспортно-логістичних послуг","discipline_eng":"Outsourcing of Transport and Logistics Services","national_grade":"Відмінно \/Excellent","credits":"4,0","ECTC":"A","mark":"95"}],"number_supplement_diploma":null,"number_diploma":null,"surname_ukr":"Артюх","practisies":[],"date_receiving_supplement":null,"surname_eng":null,"atestation":{"discipline_ukr":"1","discipline_eng":"1","national_grade":"Задовільно \/ Satisfactory","credits":"2,0","ECTC":"D","mark":"70"}},{"date_birth":"1999-10-12","total_credits":"","average_mark":"","prev_diploma_number":"В20 №141344","prev_diploma_date":"2020-07-02","name_ukr":"Марія","name_eng":null,"diploma_theme_E":null,"prev_navch_zakl":"Одеський національний морський університет","date_diploma_receiving":null,"course_works":[{"discipline_ukr":"Курсовий проект з дисципліни «Системний підхід до організації процесу доставки вантажів у міжнародному сполученні»","discipline_eng":"Course Project in System Approach to Freight Delivery in International Traffic","national_grade":"Добре \/ Good","credits":"5,0","ECTC":"C","mark":"80"}],"middlename_ukr":"Олександрівна","diploma_theme":null,"middlename_eng":null,"diploma_type":"Диплом \/ Diploma","name_dok_osv":"Диплом бакалавра","average_grade":"","series_diploma":null,"prev_navch_zakl_en":null,"average_ECTS":"","marks":[{"discipline_ukr":"Управління проектами соціальної та екологічної безпеки в транспортних системах","discipline_eng":"Management of Social and Environmental Safety Projects in Transport Systems","national_grade":"Добре \/ Good","credits":"3,0","ECTC":"C","mark":"75"},{"discipline_ukr":"Системний підхід до організації процесу доставки вантажів у міжнародному сполученні","discipline_eng":"System Approach to Freight Delivery in International Traffic","national_grade":"Відмінно \/Excellent","credits":"5,0","ECTC":"A","mark":"90"},{"discipline_ukr":"Аутсорсинг транспортно-логістичних послуг","discipline_eng":"Outsourcing of Transport and Logistics Services","national_grade":"Відмінно \/Excellent","credits":"4,0","ECTC":"A","mark":"90"}],"number_supplement_diploma":null,"number_diploma":null,"surname_ukr":"Шваннікова","practisies":[],"date_receiving_supplement":null,"surname_eng":null,"atestation":{"discipline_ukr":"1","discipline_eng":"1","national_grade":"Задовільно \/ Satisfactory","credits":"2,0","ECTC":"D","mark":"70"}}]}